README.md
setup.cfg
setup.py
examples/__init__.py
examples/measuring_the_ux/__init__.py
examples/measuring_the_ux/error_rate_plots.py
examples/measuring_the_ux/learnability_plots.py
examples/measuring_the_ux/success_rate_plots.py
examples/measuring_the_ux/task_efficiency_plots.py
examples/measuring_the_ux/task_time_plots.py
tests/__init__.py
tests/sequence_cropping.py
tests/sequence_splitting.py
tests/test_task_success.py
tests/test_time_on_task.py
tests/classes/__init__.py
tests/classes/sequences/__init__.py
tests/classes/sequences/test_sequences.py
tests/classes/wrappers/__init__.py
tests/classes/wrappers/test_map_result.py
tests/factories/__init__.py
tests/factories/test_source_target_factory.py
tests/factories/test_timing_factory.py
tests/helpers/__init__.py
ux/__init__.py
ux/compound_types.py
ux/database_manager.py
ux/location.py
ux/session.py
ux/user.py
ux.egg-info/PKG-INFO
ux.egg-info/SOURCES.txt
ux.egg-info/dependency_links.txt
ux.egg-info/requires.txt
ux.egg-info/top_level.txt
ux/actions/__init__.py
ux/actions/action_template.py
ux/actions/user_action.py
ux/calcs/__init__.py
ux/calcs/basic_calcs/__init__.py
ux/calcs/basic_calcs/efficiency.py
ux/calcs/basic_calcs/stats.py
ux/calcs/basic_calcs/task_success.py
ux/calcs/object_calcs/__init__.py
ux/calcs/object_calcs/efficiency.py
ux/calcs/object_calcs/task_success.py
ux/calcs/object_calcs/time_on_task.py
ux/calcs/object_calcs/transitions.py
ux/calcs/object_calcs/utils.py
ux/calcs/object_calcs/ux_calc.py
ux/counts/__init__.py
ux/counts/count_config.py
ux/counts/temporal_count.py
ux/kpis/__init__.py
ux/kpis/kpi.py
ux/kpis/kpi_config.py
ux/plots/__init__.py
ux/plots/helpers.py
ux/plots/transitions.py
ux/plots/versioning.py
ux/plots/usability/__init__.py
ux/plots/usability/efficiency.py
ux/plots/usability/errors.py
ux/plots/usability/learnability.py
ux/plots/usability/task_success.py
ux/plots/usability/time_on_task.py
ux/sequences/__init__.py
ux/sequences/action_sequence.py
ux/sequences/sequences.py
ux/sequences/sequences_group_by.py
ux/tasks/__init__.py
ux/tasks/task.py
ux/tasks/task_result.py
ux/utils/__init__.py
ux/utils/counts.py
