Metadata-Version: 1.0
Name: ux
Version: 0.1.15
Summary: A Python package for measuring and analyzing User Experience
Home-page: https://github.com/vahndi/ux
Author: vahndi.minah
Author-email: UNKNOWN
License: MIT
Platform: UNKNOWN
